odoo/addons/fieldservice_current_location/README.rst
odoo/addons/fieldservice_current_location/__init__.py
odoo/addons/fieldservice_current_location/__manifest__.py
odoo/addons/fieldservice_current_location/i18n/ca.po
odoo/addons/fieldservice_current_location/i18n/es.po
odoo/addons/fieldservice_current_location/i18n/fieldservice_current_location.pot
odoo/addons/fieldservice_current_location/i18n/it.po
odoo/addons/fieldservice_current_location/models/__init__.py
odoo/addons/fieldservice_current_location/models/fsm_location.py
odoo/addons/fieldservice_current_location/models/fsm_order.py
odoo/addons/fieldservice_current_location/readme/CONFIGURE.md
odoo/addons/fieldservice_current_location/readme/CONTRIBUTORS.md
odoo/addons/fieldservice_current_location/readme/DESCRIPTION.md
odoo/addons/fieldservice_current_location/readme/USAGE.md
odoo/addons/fieldservice_current_location/security/ir.model.access.csv
odoo/addons/fieldservice_current_location/static/description/icon.png
odoo/addons/fieldservice_current_location/static/description/index.html
odoo/addons/fieldservice_current_location/static/src/js/geolocate_button.esm.js
odoo/addons/fieldservice_current_location/static/src/xml/geolocate_button.xml
odoo/addons/fieldservice_current_location/tests/__init__.py
odoo/addons/fieldservice_current_location/tests/test_current_location.py
odoo/addons/fieldservice_current_location/views/fsm_order.xml
odoo_addon_fieldservice_current_location-17.0.1.1.0.dist-info/METADATA
odoo_addon_fieldservice_current_location-17.0.1.1.0.dist-info/WHEEL
odoo_addon_fieldservice_current_location-17.0.1.1.0.dist-info/top_level.txt
odoo_addon_fieldservice_current_location-17.0.1.1.0.dist-info/RECORD
